oligo_melting/__init__.py
oligo_melting/const.py
oligo_melting/duplex.py
oligo_melting/secstr.py
oligo_melting/seq.py
oligo_melting-2.0.2.data/scripts/melt_duplex
oligo_melting-2.0.2.data/scripts/melt_secstr
oligo_melting-2.0.2.dist-info/LICENSE
oligo_melting-2.0.2.dist-info/METADATA
oligo_melting-2.0.2.dist-info/WHEEL
oligo_melting-2.0.2.dist-info/top_level.txt
oligo_melting-2.0.2.dist-info/RECORD
