Metadata-Version: 2.1
Name: oligo-melting
Version: 2.0.2
Summary: A Python3 package for melting temperature calculation of         oligonucleotides hybridization and secondary structures.
Home-page: https://github.com/ggirelli/oligo-melting
Author: Gabriele Girelli
Author-email: gabriele.girelli@scilifelab.se
License: MIT
Keywords: DNA chemistry melting temperature modeling RNA salt denaturant
Platform: UNKNOWN
Classifier: Development Status :: 5 - Production/Stable
Classifier: Intended Audience :: Science/Research
Classifier: Topic :: Scientific/Engineering :: Bio-Informatics
Classifier: License :: OSI Approved :: MIT License
Classifier: Programming Language :: Python :: 3 :: Only
Requires-Dist: biopython
